ig_me/__init__.py
ig_me-0.0.0.dist-info/AUTHORS.rst
ig_me-0.0.0.dist-info/LICENSE
ig_me-0.0.0.dist-info/METADATA
ig_me-0.0.0.dist-info/WHEEL
ig_me-0.0.0.dist-info/top_level.txt
ig_me-0.0.0.dist-info/RECORD
